setup.py
NW_distributions.egg-info/PKG-INFO
NW_distributions.egg-info/SOURCES.txt
NW_distributions.egg-info/dependency_links.txt
NW_distributions.egg-info/not-zip-safe
NW_distributions.egg-info/top_level.txt
distributions/Binomialdistribution.py
distributions/Gaussiandistribution.py
distributions/Generaldistribution.py
distributions/__init__.py